pkg/__init__.py
pkg/runner.py
pkg/cmd/__init__.py
pkg/cmd/command_line.py
pkg/comment_parser/__init__.py
pkg/comment_parser/comments_parser.py
pkg/comment_parser/comments_parser_utils.py
pkg/documents/__init__.py
pkg/documents/templates/__init__.py
pkg/documents/templates/chart.py
pkg/documents/templates/chart_data.py
pkg/documents/templates/replacement.py
pkg/documents/templates/requirement_data.py
pkg/documents/templates/requirements.py
pkg/documents/templates/values.py
pkg/helm/Template.py
pkg/helm/__init__.py
pkg/helm/charts_finder.py
pkg/helm/utils.py
pkg/values_parser/__init__.py
pkg/values_parser/values_parser_utils.py
pkg/values_parser/values_section.py
pkg/values_parser/table_formate/__init__.py
pkg/values_parser/table_formate/formate_table.py
helm2readme-1.1.4.dist-info/METADATA
helm2readme-1.1.4.dist-info/WHEEL
helm2readme-1.1.4.dist-info/entry_points.txt
helm2readme-1.1.4.dist-info/top_level.txt
helm2readme-1.1.4.dist-info/RECORD
